<datasources>
    <datasource jndi-name="java:/StudentsDataSource" pool-name="StudentsDataSourcePool" enabled="true" use-java-context="true">
        <driver>h2</driver>
        <connection-url>jdbc:h2:~/h2database/DemoDB;AUTO_SERVER=true</connection-url>
        <security>
            <user-name>sa</user-name>
            <password>sa</password>
        </security>
    </datasource>
    <drivers>
        <driver name="h2" module="com.h2database.h2">
            <xa-datasource-class>org.h2.jdbcx.JdbcDataSource</xa-datasource-class>
        </driver>
    </drivers>
</datasources>